README.md
setup.py
ch_filing/__init__.py
ch_filing/client.py
ch_filing/company_data.py
ch_filing/envelope.py
ch_filing/form_submission.py
ch_filing/state.py
ch_filing/submission_status.py
gnucash_ch_filing.egg-info/PKG-INFO
gnucash_ch_filing.egg-info/SOURCES.txt
gnucash_ch_filing.egg-info/dependency_links.txt
gnucash_ch_filing.egg-info/requires.txt
gnucash_ch_filing.egg-info/top_level.txt
scripts/ch-filing