Metadata-Version: 2.1
Name: gnucash-ch-filing
Version: 0.2.1
Summary: UK Companies House accounts filing for GnuCash users
Home-page: https://github.com/cybermaggedon/gnucash-ch-filing
Author: Cybermaggedon
Author-email: mark@cyberapocalypse.co.uk
License: UNKNOWN
Download-URL: https://github.com/cybermaggedon/gnucash-uk-corptax/archive/refs/tags/v0.2.1.tar.gz
Platform: UNKNOWN
Classifier: Programming Language :: Python :: 3
Classifier: License :: OSI Approved :: GNU General Public License v3 or later (GPLv3+)
Classifier: Operating System :: OS Independent
Requires-Python: >=3.6
